gpt_fn/__init__.py
gpt_fn/ai_function.py
gpt_fn/completion.py
gpt_fn/conftest.py
gpt_fn/exceptions.py
gpt_fn/prompt.py
gpt_fn/py.typed
gpt_fn/tests/__init__.py
gpt_fn/tests/__snapshots__/test_ai_function.ambr
gpt_fn/tests/__snapshots__/test_completion.ambr
gpt_fn/tests/__snapshots__/test_prompt.ambr
gpt_fn/tests/cassettes/test_ai_function/test_ai_fabnocci.yaml
gpt_fn/tests/cassettes/test_ai_function/test_ai_fake_hero.yaml
gpt_fn/tests/cassettes/test_ai_function/test_ai_fn_max_token.yaml
gpt_fn/tests/cassettes/test_completion/test_achat_completion[Azure 2024-05-01 API].yaml
gpt_fn/tests/cassettes/test_completion/test_achat_completion[OpenAI API].yaml
gpt_fn/tests/cassettes/test_completion/test_afunction_completion[Azure 2024-05-01 API].yaml
gpt_fn/tests/cassettes/test_completion/test_afunction_completion[OpenAI API].yaml
gpt_fn/tests/cassettes/test_completion/test_astructural_completion[Azure 2024-05-01 API].yaml
gpt_fn/tests/cassettes/test_completion/test_astructural_completion[OpenAI API].yaml
gpt_fn/tests/cassettes/test_completion/test_chat_completion[Azure 2024-05-01 API].yaml
gpt_fn/tests/cassettes/test_completion/test_chat_completion[OpenAI API].yaml
gpt_fn/tests/cassettes/test_completion/test_chat_completion_incomplete[Azure 2024-05-01 API].yaml
gpt_fn/tests/cassettes/test_completion/test_chat_completion_incomplete[OpenAI API].yaml
gpt_fn/tests/cassettes/test_completion/test_function_completion[Azure 2024-05-01 API].yaml
gpt_fn/tests/cassettes/test_completion/test_function_completion[OpenAI API].yaml
gpt_fn/tests/cassettes/test_completion/test_function_completion_without_enough_tokens[Azure 2024-05-01 API].yaml
gpt_fn/tests/cassettes/test_completion/test_function_completion_without_enough_tokens[OpenAI API].yaml
gpt_fn/tests/cassettes/test_completion/test_function_completion_without_neccess_function[Azure 2024-05-01 API].yaml
gpt_fn/tests/cassettes/test_completion/test_function_completion_without_neccess_function[OpenAI API].yaml
gpt_fn-0.2.0.dist-info/LICENSE
gpt_fn-0.2.0.dist-info/METADATA
gpt_fn-0.2.0.dist-info/WHEEL
gpt_fn-0.2.0.dist-info/RECORD
