Metadata-Version: 2.3
Name: gpt-fn
Version: 0.2.0
Summary: 
Author: lucemia
Author-email: lucemia@gmail.com
Requires-Python: >=3.10,<4.0
Classifier: Programming Language :: Python :: 3
Classifier: Programming Language :: Python :: 3.10
Classifier: Programming Language :: Python :: 3.11
Classifier: Programming Language :: Python :: 3.12
Classifier: Programming Language :: Python :: 3.13
Requires-Dist: docstring-parser
Requires-Dist: fuzy-jon
Requires-Dist: jinja2
Requires-Dist: langchain-core (>=0.3.49,<0.4.0)
Requires-Dist: openai (>=1.0.0)
Requires-Dist: pydantic (>=2,<3)
